{
    "startRound": 6,
    "hero": "ETIENNE",
    "towers": {
      "etienne": {
        "type": "HERO",
        "coords": [645, 382]
      },
      "farm1": {
        "type": "BANANA",
        "coords": [60, 539]
      },
      "farm2": {
        "type": "BANANA",
        "coords": [1233, 538]
      },
      "ace": {
        "type": "ACE",
        "coords": [945, 750]
      },
      "sniper": {
        "type": "SNIPER",
        "coords": [313, 646]
      },
      "druid": {
        "type": "DRUID",
        "coords": [365, 265]
      },
      "boat": {
        "type": "BUCCANEER",
        "coords": [380, 720]
      },
      "alchemist": {
        "type": "ALCHEMIST",
        "coords": [382, 605]
      },
      "spike": {
        "type": "SPIKE",
        "coords": [650, 644]
      }
    },
    "instructions": {
      "milestones": [7, 8, 10, 14, 16, 23, 25, 29, 36, 37, 38, 39, 40, 49, 54, 55, 56, 57, 78, 83, 87, 95], 
      "start": ["place etienne", "place boat"],
      "7": ["upgrade boat 2"],
      "8": ["place druid"],
      "10": ["upgrade druid 1 2"],
      "14": ["upgrade druid 2 2"],
      "16": ["place farm1"],
      "23": ["upgrade farm1 3 3 3"],
      "25": ["upgrade farm1 2 2"],
      "29": ["upgrade boat 1 1 1 2"],
      "36": ["upgrade boat 1"],
      "37": ["place farm2"],
      "38": ["upgrade farm2 3 3 3 2 2"],
      "39": ["place ace", "upgrade ace 3 3 1", "change ace 1"],
      "40": ["upgrade ace 3 1"],
      "49": ["upgrade boat 1"],
      "54": ["upgrade ace 3"],
      "55": ["place sniper", "upgrade sniper 1 1 1 3 3", "change sniper 3"],
      "56": ["change sniper 1"],
      "57": ["place alchemist", "upgrade alchemist 1 1 1 1 2"],
      "78": ["upgrade ace 3"],
      "83": ["upgrade druid 2 2"],
      "87": ["upgrade sniper 1"],
      "95": ["place spike", "upgrade spike 2 2 2 2 2 1 1"]
    }
  }
  